round_percentages/__init__.py
round_percentages/round_percentages.py
round_percentages-1.0.dist-info/LICENSE
round_percentages-1.0.dist-info/METADATA
round_percentages-1.0.dist-info/WHEEL
round_percentages-1.0.dist-info/top_level.txt
round_percentages-1.0.dist-info/RECORD
